{"[UNK]":0,"[PAD]":1,"[START]":2,"[END]":3,"!":4,"a":5,"c":6,"d":7,"e":8,"f":9,"g":10,"h":11,"i":12,"l":13,"m":14,"n":15,"o":16,"p":17,"r":18,"s":19,"t":20,"u":21,"v":22,"w":23,"x":24,"y":25,"z":26,"’":27,"oo":28,"is":29,"ha":30,"coo":31,"his":32,"in":33,"re":34,"this":35,"hat":36,"cool":37,"ing":38,"aa":39,"am":40,"are":41,"ed":42,"ey":43,"hey":44,"ou":45,"ow":46,"so":47,"what":48,"you":49,"an":50,"ax":51,"ay":52,"az":53,"ci":54,"do":55,"ee":56,"ex":57,"fu":58,"fee":59,"goo":60,"how":61,"lo":62,"ling":63,"lax":64,"nn":65,"now":66,"pp":67,"soo":68,"that":69,"ted":70,"up":71,"ve":72,"yy":73,"yaa":74,"happ":75,"relax":76,"amaz":77,"heyyy":78,"and":79,"cited":80,"doing":81,"excited":82,"funn":83,"feeling":84,"good":85,"love":86,"sooo":87,"yaaay":88,"happy":89,"relaxed":90,"amazing":91,"funny":92}